alpha_flex/__init__.py
alpha_flex/backtest.py
alpha_flex/filters.py
alpha_flex/portfolio.py
alpha_flex/version.py
alpha_flex-1.14.8.dist-info/LICENSE
alpha_flex-1.14.8.dist-info/METADATA
alpha_flex-1.14.8.dist-info/WHEEL
alpha_flex-1.14.8.dist-info/top_level.txt
alpha_flex-1.14.8.dist-info/RECORD
