Metadata-Version: 2.1
Name: alpha_flex
Version: 1.14.8
Summary: AlphaFlex is a Python toolkit featuring a pre-built growth-focused portfolio that consistently outperforms the market. It provides tools for portfolio tracking, backtesting, and automated updates, with the ability to integrate directly with brokerage accounts for seamless trading and quarterly rebalancing.
Home-page: https://github.com/esobimpe/alpha_flex
Author: Eniola Sobimpe
Author-email: sobimpeeniola@gmail.com
Classifier: Programming Language :: Python :: 3
Classifier: License :: OSI Approved :: Apache Software License
Classifier: Operating System :: OS Independent
Requires-Python: >=3.7
License-File: LICENSE
Requires-Dist: yfinance
Requires-Dist: numpy
Requires-Dist: pandas
Requires-Dist: finvizfinance
